{"name@lisperanto":"open_OmniBox_for_adding_text_value_to_json_entry","type@lisperanto":"function","module@lisperanto":"lisperanto","programming-language@lisperanto":"javascript","javascript-function-definition@lisperanto":"async function(caller)\r\n{\r\n    lisperanto.hideOmniBox();\r\n    lisperanto.focusedObj(caller);\r\n    lisperanto.activeOperation(\"add-text-value-to-json-entry\");\r\n\r\n    const id = await caller.id();\r\n\r\n    lisperanto.filloutOmniBoxDataForFunction(`#${id} #add-text-value-to-json-entry--`, lisperanto.canvasOmniBox, caller);\r\n}"}