{"operation":"create-initial-version","id_to":"3e4e85c8dd9a4b20b434f5477e82383de896d2c0c13ad92e1e22e6b3ed59484b","initial-data":{"name@lisperanto":"omniBoxOnWheel","type@lisperanto":"function","module@lisperanto":"lisperanto","programming-language@lisperanto":"javascript","previous-version@lisperanto":"dd7aff41855d4a7021d12b92a568d8042e51bd5efc492b10db8abf3b75ea2198","javascript-function-definition@lisperanto":"function()\r\n{\r\n    // i need this to block scroll event, probably\r\n    event.stopPropagation();\r\n}"},"time":"2022-09-24 23:46:50 (+3)"}